etc/logrotate.d/okconfig
okconfig/__init__.py
okconfig/config.py
okconfig/helper_functions.py
okconfig/migration_tool.py
okconfig/network_scan.py
okconfig-1.4.2.data/scripts/okconfig
usr/share/okconfig/perfdata-graphs.cfg
usr/share/okconfig/pnp4nagios.cfg
usr/share/okconfig/pretty-nagios-emails.cfg
usr/share/okconfig/client/linux/install_okagent.sh
usr/share/okconfig/client/windows/install_nsclient.sh
usr/share/okconfig/examples/3par.cfg-example
usr/share/okconfig/examples/aix.cfg-example
usr/share/okconfig/examples/apache.cfg-example
usr/share/okconfig/examples/apc-acrc.cfg-example
usr/share/okconfig/examples/apc-acsc.cfg-example
usr/share/okconfig/examples/apc-cooling.cfg-example
usr/share/okconfig/examples/apc-netbotz.cfg-example
usr/share/okconfig/examples/apc-rpdu.cfg-example
usr/share/okconfig/examples/apc-ups.cfg-example
usr/share/okconfig/examples/autodiscover.cfg-example
usr/share/okconfig/examples/bladecenter.cfg-example
usr/share/okconfig/examples/brocade.cfg-example
usr/share/okconfig/examples/ciscoasa.cfg-example
usr/share/okconfig/examples/ciscoswitch.cfg-example
usr/share/okconfig/examples/counter-mssql.cfg-example
usr/share/okconfig/examples/dataprotector.cfg-example
usr/share/okconfig/examples/dell.cfg-example
usr/share/okconfig/examples/dns.cfg-example
usr/share/okconfig/examples/drbd.cfg-example
usr/share/okconfig/examples/emc.cfg-example
usr/share/okconfig/examples/eva.cfg-example
usr/share/okconfig/examples/exchange.cfg-example
usr/share/okconfig/examples/group.cfg-example
usr/share/okconfig/examples/host-passive.cfg-example
usr/share/okconfig/examples/host.cfg-example
usr/share/okconfig/examples/hpasm.cfg-example
usr/share/okconfig/examples/hplibrary.cfg-example
usr/share/okconfig/examples/hpprocurve.cfg-example
usr/share/okconfig/examples/http.cfg-example
usr/share/okconfig/examples/https.cfg-example
usr/share/okconfig/examples/iis.cfg-example
usr/share/okconfig/examples/ipa.cfg-example
usr/share/okconfig/examples/ironport.cfg-example
okconfig-1.4.2.dist-info/AUTHORS
okconfig-1.4.2.dist-info/LICENSE
okconfig-1.4.2.dist-info/METADATA
okconfig-1.4.2.dist-info/WHEEL
okconfig-1.4.2.dist-info/top_level.txt
okconfig-1.4.2.dist-info/RECORD
