Metadata-Version: 2.1
Name: okconfig
Version: 1.4.2
Summary: okconfig - Powertools to generate Nagios configuration files
Home-page: http://okconfig.org
Author: Pall Sigurdsson
Author-email: palli@opensource.is
Maintainer: Gardar Thorsteinsson
Maintainer-email: gardar@ok.is
License: GPL
Platform: UNKNOWN
Requires: unittest2
License-File: LICENSE
License-File: AUTHORS
Requires-Dist: paramiko
Requires-Dist: pynag
Requires-Dist: six
Requires-Dist: future
Requires-Dist: setuptools-rust
